aiotinydb/__init__.py
aiotinydb/database.py
aiotinydb/exceptions.py
aiotinydb/filelock.py
aiotinydb/middleware.py
aiotinydb/py.typed
aiotinydb/storage.py
aiotinydb-2.0.0.dist-info/LICENSE.md
aiotinydb-2.0.0.dist-info/WHEEL
aiotinydb-2.0.0.dist-info/METADATA
aiotinydb-2.0.0.dist-info/RECORD
