Metadata-Version: 2.1
Name: aiotinydb
Version: 2.0.0
Summary: asyncio compatibility shim for tinydb
Author-email: Pavel Pletenev <cpp.create@gmail.com>
Maintainer-email: d-k-bo <d-k-bo@mailbox.org>
Requires-Python: >=3.7
Classifier: License :: OSI Approved :: GNU Lesser General Public License v3 or later (LGPLv3+)
Classifier: Development Status :: 4 - Beta
Classifier: Programming Language :: Python :: 3
Classifier: Programming Language :: Python :: 3.7
Classifier: Programming Language :: Python :: 3.8
Classifier: Programming Language :: Python :: 3.9
Classifier: Programming Language :: Python :: 3.10
Classifier: Programming Language :: Python :: 3.11
Classifier: Topic :: Software Development :: Libraries :: Python Modules
Classifier: Operating System :: OS Independent
Classifier: Intended Audience :: Developers
Requires-Dist: tinydb>=4.7.0
Requires-Dist: aiofiles>=0.8.0
Requires-Dist: pytest>=7.0.1 ; extra == "test"
Requires-Dist: pytest-cov>=3.0.0 ; extra == "test"
Project-URL: Source, https://github.com/aiotinydb/aiotinydb
Provides-Extra: test
